{
  "type": "minecraft:entity",
  "pools": [
    {
      "bonus_rolls": 0.0,
      "conditions": [
        {
          "condition": "minecraft:entity_properties",
          "entity": "this",
          "predicate": {
            "type": "minecraft:phantom"
          }
        },
        {
          "chance": 0.1,
          "condition": "minecraft:random_chance"
        }
      ],
      "entries": [
        {
          "type": "minecraft:item",
          "name": "ltxi:targeting_tech_salvage"
        }
      ],
      "rolls": 1.0
    },
    {
      "bonus_rolls": 0.0,
      "conditions": [
        {
          "condition": "minecraft:entity_properties",
          "entity": "this",
          "predicate": {
            "type": "minecraft:warden"
          }
        },
        {
          "condition": "minecraft:any_of",
          "terms": [
            {
              "condition": "minecraft:entity_properties",
              "entity": "direct_attacker",
              "predicate": {
                "type_specific": {
                  "type": "ltxi:grenade_type",
                  "grenade_element": "acid"
                }
              }
            },
            {
              "condition": "minecraft:entity_properties",
              "entity": "this",
              "predicate": {
                "effects": {
                  "ltxi:corrosive": {}
                }
              }
            }
          ]
        }
      ],
      "entries": [
        {
          "type": "minecraft:item",
          "name": "ltxi:neuro_chemical"
        }
      ],
      "rolls": 1.0
    }
  ],
  "random_sequence": "ltxi:entity/extra_drops"
}