{
  "type": "minecraft:block",
  "pools": [
    {
      "bonus_rolls": 0.0,
      "conditions": [
        {
          "condition": "minecraft:survives_explosion"
        },
        {
          "block": "limatech:rocket_turret",
          "condition": "minecraft:block_state_property",
          "properties": {
            "half": "lower"
          }
        }
      ],
      "entries": [
        {
          "type": "minecraft:item",
          "name": "limatech:rocket_turret"
        }
      ],
      "functions": [
        {
          "function": "limacore:save_block_entity"
        }
      ],
      "rolls": 1.0
    }
  ],
  "random_sequence": "limatech:blocks/rocket_turret"
}