{
	"_license": "(C) 2026 Eduardo Jimenez | CC BY-NC-SA 4.0",
	"_credit": "Made with Blockbench",
	"ambientocclusion": false,
	"texture_size": [32, 32],
	"loader": "limacore:item_layers",
	"render_type": "solid",
	"layers": [
		{
			"name": "frame",
			"groups": ["frame"]
		},
		{
			"name": "blades",
			"groups": ["blades"]
		},
		{
			"name": "lights",
			"groups": ["lights"],
			"emissivity": 15,
			"render_type": "limacore:emissive"
		},
		{
			"name": "tank",
			"groups": ["tank"],
			"render_type": "translucent"
		}
	],
	"textures": {
		"frame0": "ltxi:block/titanium_panel",
		"frame1": "ltxi:block/smooth_slatesteel_panel",
		"frame2": "ltxi:block/mixer",
		"glass": "ltxi:glass",
		"lights": "ltxi:solid_lime"
	},
	"elements": [
		{
			"from": [0, 0, 0],
			"to": [16, 4, 16],
			"faces": {
				"north": { "uv": [0, 0, 8, 2], "texture": "#frame2" },
				"east": { "uv": [0, 0, 8, 2], "texture": "#frame2" },
				"south": { "uv": [0, 0, 8, 2], "texture": "#frame2" },
				"west": { "uv": [0, 0, 8, 2], "texture": "#frame2" },
				"up": { "uv": [0, 0, 16, 16], "texture": "#frame0" },
				"down": { "uv": [0, 0, 16, 16], "texture": "#frame1" }
			}
		},
		{
			"from": [1, 4, 1],
			"to": [15, 5, 15],
			"faces": {
				"north": { "uv": [15, 0, 8, 0.5], "texture": "#frame2" },
				"east": { "uv": [14.5, 0, 15, 7], "rotation": 90, "texture": "#frame2" },
				"south": { "uv": [8, 6.5, 15, 7], "texture": "#frame2" },
				"west": { "uv": [8, 7, 8.5, 0], "rotation": 90, "texture": "#frame2" },
				"up": { "uv": [8, 0, 15, 7], "texture": "#frame2" }
			}
		},
		{
			"from": [1, 13, 1],
			"to": [15, 15, 15],
			"faces": {
				"north": { "uv": [8, 14, 15, 15], "texture": "#frame2" },
				"east": { "uv": [8, 14, 15, 15], "texture": "#frame2" },
				"south": { "uv": [8, 14, 15, 15], "texture": "#frame2" },
				"west": { "uv": [8, 14, 15, 15], "texture": "#frame2" },
				"up": { "uv": [8, 7, 15, 14], "texture": "#frame2" },
				"down": { "uv": [8, 7, 15, 14], "texture": "#frame2" }
			}
		},
		{
			"from": [2, 15, 2],
			"to": [14, 16, 14],
			"faces": {
				"north": { "uv": [6, 2, 0, 2.5], "texture": "#frame2" },
				"east": { "uv": [5.5, 2, 6, 8], "rotation": 90, "texture": "#frame2" },
				"south": { "uv": [0, 7.5, 6, 8], "texture": "#frame2" },
				"west": { "uv": [0, 8, 0.5, 2], "rotation": 90, "texture": "#frame2" },
				"up": { "uv": [0, 2, 6, 8], "texture": "#frame2" }
			}
		},
		{
			"from": [7, 5, 7],
			"to": [9, 13, 9],
			"faces": {
				"north": { "uv": [0, 8, 1, 12], "texture": "#frame2" },
				"east": { "uv": [0, 8, 1, 12], "texture": "#frame2" },
				"south": { "uv": [0, 8, 1, 12], "texture": "#frame2" },
				"west": { "uv": [0, 8, 1, 12], "texture": "#frame2" }
			}
		},
		{
			"from": [5, 2, 0],
			"to": [11, 6, 1],
			"rotation": { "angle": 22.5, "axis": "x", "origin": [8, 4, 0.5] },
			"faces": {
				"north": { "uv": [2.5, 8, 5.5, 10], "texture": "#frame2" },
				"east": { "uv": [2.5, 8, 3, 10], "texture": "#frame2" },
				"south": { "uv": [2.5, 10, 5.5, 12], "texture": "#frame2" },
				"west": { "uv": [5, 8, 5.5, 10], "texture": "#frame2" },
				"up": { "uv": [2.5, 8, 5.5, 8.5], "texture": "#frame2" },
				"down": { "uv": [2.5, 9.5, 5.5, 10], "texture": "#frame2" }
			}
		},
		{
			"from": [5, 0.625, -0.01],
			"to": [11, 1.375, 0],
			"faces": {
				"north": { "uv": [1, 0.625, 4, 1], "texture": "#lights" }
			}
		},
		{
			"from": [-0.01, 0.625, 5],
			"to": [0, 1.375, 11],
			"faces": {
				"west": { "uv": [1, 0.625, 4, 1], "texture": "#lights" }
			}
		},
		{
			"from": [16, 0.625, 5],
			"to": [16.01, 1.375, 11],
			"faces": {
				"east": { "uv": [1, 0.625, 4, 1], "texture": "#lights" }
			}
		},
		{
			"from": [5, 0.625, 16],
			"to": [11, 1.375, 16.01],
			"faces": {
				"south": { "uv": [4, 0.625, 1, 1], "texture": "#lights" }
			}
		},
		{
			"from": [2, 5, 2],
			"to": [14, 5.01, 2.5],
			"faces": {
				"up": { "uv": [1, 1, 7, 1.25], "texture": "#lights" }
			}
		},
		{
			"from": [2, 5, 13.5],
			"to": [14, 5.01, 14],
			"faces": {
				"up": { "uv": [1, 1, 7, 1.25], "texture": "#lights" }
			}
		},
		{
			"from": [2, 5, 2.5],
			"to": [2.5, 5.01, 13.5],
			"faces": {
				"up": { "uv": [1, 2, 1.25, 7.5], "texture": "#lights" }
			}
		},
		{
			"from": [13.5, 5, 2.5],
			"to": [14, 5.01, 13.5],
			"faces": {
				"up": { "uv": [1, 1, 1.25, 6.5], "texture": "#lights" }
			}
		},
		{
			"from": [5.5, 13.5, 0.99],
			"to": [10.5, 14, 1],
			"faces": {
				"north": { "uv": [1, 1.25, 3.5, 1.5], "texture": "#lights" }
			}
		},
		{
			"from": [0.99, 13.5, 5.5],
			"to": [1, 14, 10.5],
			"faces": {
				"west": { "uv": [1, 1.25, 3.5, 1.5], "texture": "#lights" }
			}
		},
		{
			"from": [15, 13.5, 5.5],
			"to": [15.01, 14, 10.5],
			"faces": {
				"east": { "uv": [1, 1.25, 3.5, 1.5], "texture": "#lights" }
			}
		},
		{
			"from": [5.5, 13.5, 15],
			"to": [10.5, 14, 15.01],
			"faces": {
				"south": { "uv": [3.5, 1.25, 1, 1.5], "texture": "#lights" }
			}
		},
		{
			"from": [5.99, 2.99, -0.01],
			"to": [10.01, 5.01, 1.01],
			"rotation": { "angle": 22.5, "axis": "x", "origin": [8, 4, 0.5] },
			"faces": {
				"north": { "uv": [0, 12, 4, 14], "texture": "#frame2" }
			}
		},
		{
			"from": [6.99, 5.99, 6.99],
			"to": [9.01, 6.51, 9.01],
			"faces": {
				"north": { "uv": [1, 1, 2, 2], "texture": "#lights" },
				"east": { "uv": [1, 1, 2, 2], "texture": "#lights" },
				"south": { "uv": [1, 1, 2, 2], "texture": "#lights" },
				"west": { "uv": [1, 1, 2, 2], "texture": "#lights" }
			}
		},
		{
			"from": [6.99, 11.49, 6.99],
			"to": [9.01, 12.01, 9.01],
			"faces": {
				"north": { "uv": [1, 1, 2, 2], "texture": "#lights" },
				"east": { "uv": [1, 1, 2, 2], "texture": "#lights" },
				"south": { "uv": [1, 1, 2, 2], "texture": "#lights" },
				"west": { "uv": [1, 1, 2, 2], "texture": "#lights" }
			}
		},
		{
			"from": [1.5, 5, 1.5],
			"to": [14.5, 13, 14.5],
			"faces": {
				"north": { "uv": [0, 0, 6.5, 4], "texture": "#glass" },
				"east": { "uv": [0, 0, 6.5, 4], "texture": "#glass" },
				"south": { "uv": [0, 0, 6.5, 4], "texture": "#glass" },
				"west": { "uv": [0, 0, 6.5, 4], "texture": "#glass" }
			}
		},
		{
			"from": [6.5, 8, 3],
			"to": [9.5, 9, 7],
			"rotation": { "angle": 45, "axis": "z", "origin": [8, 8.5, 5] },
			"faces": {
				"north": { "uv": [2.5, 8, 1, 8.5], "texture": "#frame2" },
				"east": { "uv": [2, 8, 2.5, 10], "rotation": 90, "texture": "#frame2" },
				"south": { "uv": [1, 9.5, 2.5, 10], "texture": "#frame2" },
				"west": { "uv": [1, 10, 1.5, 8], "rotation": 90, "texture": "#frame2" },
				"up": { "uv": [1, 8, 2.5, 10], "texture": "#frame2" },
				"down": { "uv": [1, 10, 2.5, 8], "texture": "#frame2" }
			}
		},
		{
			"from": [9, 8, 6.5],
			"to": [13, 9, 9.5],
			"rotation": { "angle": -45, "axis": "x", "origin": [11, 8.5, 8] },
			"faces": {
				"north": { "uv": [1, 10, 1.5, 8], "rotation": 90, "texture": "#frame2" },
				"east": { "uv": [2.5, 8, 1, 8.5], "texture": "#frame2" },
				"south": { "uv": [2, 8, 2.5, 10], "rotation": 90, "texture": "#frame2" },
				"west": { "uv": [1, 9.5, 2.5, 10], "texture": "#frame2" },
				"up": { "uv": [1, 8, 2.5, 10], "rotation": 90, "texture": "#frame2" },
				"down": { "uv": [1, 10, 2.5, 8], "rotation": 270, "texture": "#frame2" }
			}
		},
		{
			"from": [3, 8, 6.5],
			"to": [7, 9, 9.5],
			"rotation": { "angle": 45, "axis": "x", "origin": [5, 8.5, 8] },
			"faces": {
				"north": { "uv": [2, 8, 2.5, 10], "rotation": 90, "texture": "#frame2" },
				"east": { "uv": [1, 9.5, 2.5, 10], "texture": "#frame2" },
				"south": { "uv": [1, 10, 1.5, 8], "rotation": 90, "texture": "#frame2" },
				"west": { "uv": [2.5, 8, 1, 8.5], "texture": "#frame2" },
				"up": { "uv": [1, 8, 2.5, 10], "rotation": 270, "texture": "#frame2" },
				"down": { "uv": [1, 10, 2.5, 8], "rotation": 90, "texture": "#frame2" }
			}
		},
		{
			"from": [6.5, 8, 9],
			"to": [9.5, 9, 13],
			"rotation": { "angle": -45, "axis": "z", "origin": [8, 8.5, 11] },
			"faces": {
				"north": { "uv": [2.5, 9.5, 1, 10], "rotation": 180, "texture": "#frame2" },
				"east": { "uv": [1, 8, 1.5, 10], "rotation": 270, "texture": "#frame2" },
				"south": { "uv": [1, 8, 2.5, 8.5], "rotation": 180, "texture": "#frame2" },
				"west": { "uv": [2, 10, 2.5, 8], "rotation": 270, "texture": "#frame2" },
				"up": { "uv": [1, 8, 2.5, 10], "rotation": 180, "texture": "#frame2" },
				"down": { "uv": [1, 10, 2.5, 8], "rotation": 180, "texture": "#frame2" }
			}
		}
	],
	"display": {
		"thirdperson_righthand": {
			"rotation": [75, 45, 0],
			"translation": [0, 2.5, 0],
			"scale": [0.375, 0.375, 0.375]
		},
		"thirdperson_lefthand": {
			"rotation": [75, 45, 0],
			"translation": [0, 2.5, 0],
			"scale": [0.375, 0.375, 0.375]
		},
		"firstperson_righthand": {
			"rotation": [0, 135, 0],
			"translation": [0, 1, 0],
			"scale": [0.4, 0.4, 0.4]
		},
		"firstperson_lefthand": {
			"rotation": [0, 135, 0],
			"translation": [0, 1, 0],
			"scale": [0.4, 0.4, 0.4]
		},
		"ground": {
			"scale": [0.25, 0.25, 0.25]
		},
		"gui": {
			"rotation": [30, 135, 0],
			"scale": [0.625, 0.625, 0.625]
		},
		"fixed": {
			"scale": [0.5, 0.5, 0.5]
		},
		"on_shelf": {
			"rotation": [0, -180, 0]
		}
	},
	"groups": [
		{
			"name": "frame",
			"children": [0, 1, 2, 3, 4, 5]
		},
		{
			"name": "lights",
			"children": [6, 7, 8, 9, 10, 11, 12, 13, 14, 15, 16, 17, 18, 19, 20]
		},
		{
			"name": "tank",
			"children": [21]
		},
		{
			"name": "blades",
			"children": [22, 23, 24, 25]
		}
	]
}