{
  "type": "limatech:fabricating",
  "energy_required": 400000,
  "group": "weapons",
  "ingredients": [
    {
      "count": 16,
      "item": "limatech:titanium_ingot"
    },
    {
      "count": 8,
      "item": "limatech:copper_circuit"
    },
    {
      "count": 4,
      "item": "limatech:gold_circuit"
    }
  ],
  "result": {
    "components": {
      "!minecraft:enchantments": {},
      "limatech:ammo_source": "normal",
      "limatech:equipment_upgrades": {
        "limatech:lightfrag_armor_bypass": 1,
        "limatech:smg_built_in": 1
      },
      "minecraft:attribute_modifiers": {
        "modifiers": [],
        "show_in_tooltip": false
      }
    },
    "count": 1,
    "id": "limatech:submachine_gun"
  }
}